random_delay/__init__.py
random_delay/cli.py
random_delay/context_managers.py
random_delay/core.py
random_delay/decorators.py
random_delay/exceptions.py
random_delay/utils.py
random_delay-1.0.0.dist-info/METADATA
random_delay-1.0.0.dist-info/WHEEL
random_delay-1.0.0.dist-info/entry_points.txt
random_delay-1.0.0.dist-info/top_level.txt
random_delay-1.0.0.dist-info/RECORD
